pliki/gpioemu.v
/* verilator lint_off UNUSED */
/* verilator lint_off MULTIDRIVEN */
/* verilator lint_off UNDRIVEN */
/* verilator lint_off COMBDLY */
/* verilator lint_off WIDTH */
/* verilator lint_off BLKSEQ */
/* verilator lint_off BLKANDNBLK */
/* verilator lint_off CASEINCOMPLETE */

module gpioemu(n_reset,             // magistrala CPU
    saddress[15:0], srd, swr,       // wektor 16 bitowy reprezentujący adresy
    sdata_in[31:0], sdata_out[31:0], //dane wejściowe
    gpio_in[31:0], gpio_latch,      // styk GPIO - wejscia
    gpio_out[31:0],                 // styk GPIO = wyjscia
    clk,                            // zegar 1kHz
    gpio_in_s_insp[31:0]);          // sygnały testowe, inspekcyjne


    
	input 				clk;
	input 				n_reset;

	input  [15:0] 		saddress;
	input 				srd;
	input 				swr;
	input  [31:0] 		sdata_in;
    output [31:0] 		sdata_out;
    reg    [31:0]       sdata_out_s;

	input  [31:0] 		gpio_in;
    reg    [31:0]       gpio_in_s;
	input				gpio_latch;
    output [31:0]       gpio_in_s_insp;
	
	output [31:0] 		gpio_out;
    reg    [31:0]       gpio_out_s;

    reg  [23:0]       A1;  // Pierwsza liczba - 24 bity
    reg  [23:0]       A2;  // Druga liczba - 24 bity
    reg  [31:0]       W;   // Wynik mnozenia - 32 bity
    reg  [31:0]       L;   // Liczba jedynek, ktore wystapily w wyniku
    reg  [1:0]       B;   // Stan operacji: czy zakończona - 1, czy poprawna - 0, czy przepelnienie - 2;

	reg	 [47:0]		  temp; // Zmienna tymczasowa potrzebna do wykonania mnozenia - 24 bity * 2 = 48 bitow

	integer mul_i = 0; // Zmienna całkowitoliczbowa potrzebna w działaniu mnożenia
	integer ones_i = 0; // Zmienna całkowitoliczbowa potrzebna w działaniu zliczania jedynek



    always @(posedge gpio_latch) // Przypisanie po wykryciu narastajacego zbocza gpio_latch, gpio_in do rejestru gpio_in_s
	    begin
		    gpio_in_s <= gpio_in;
	    end

    always @(negedge n_reset) // Wyzerowanie zmiennych, po wykryciu sygnału resetu
	    begin
		    sdata_out_s <= 0;
		    gpio_out_s <= 0;
            A1 <= 0;
            A2 <= 0;
		    W <= 0;
		    L <= 0;
		    B <= 16'h0; 
		    mul_i <= 0;
		    ones_i <= 0;
		    temp <= 0;
	    end



    always @(posedge swr) // Blok odpowiedzialny za odczyt danych wejściowych, czyli liczb, jesli zostana odczytane, nastepuje zmiana flagi B
        begin
            if (B == 0) begin
                case(saddress)
                    16'h108: begin
                        A1 <= sdata_in;
                        W <= 0;
                        L <= 0;
                        B <= 0;
                    end
                    16'h110: begin
                        A2 <= sdata_in;
                        B <= 16'h1;
                    end
                endcase
            end
        end



    always @(posedge srd) // Blok odpowiedzialny za przekazanie danych wyjściowych
		begin
            case(saddress)                     
                16'h108: sdata_out_s <= A1;
                16'h110: sdata_out_s <= A2;
                16'h118: sdata_out_s <= W;
                16'h120: sdata_out_s <= L;
                16'h128: sdata_out_s <= B;
                default: sdata_out_s <= 0;
            endcase
		end



    always @(posedge clk) begin
        if (B == 1) begin
            temp <= 0;

            // Petla mnozy liczby metoda bit po bicie
            for (mul_i = 0; mul_i < 23; mul_i = mul_i + 1) begin
                if(A2[mul_i] == 1)
                begin
                    temp = temp + (A1<<mul_i);
                end
            end

            // Petla zlicza jedynki, jesli wystapila jedynka, nastepuje dodanie jej do wyniku
            for (ones_i = 0; ones_i < 47; ones_i = ones_i + 1) begin
                L = L + (temp[ones_i] == 1);
            end
            
            // Sprawdzenie czy nieprzepełnione, jeśli nie - koniec działań, ustawioenie flagi B na 0
            if (temp < 2**32) begin
                
                W <= temp;
                B <= 16'h0;
            end

            // Jeśli przepełnione, ustawienie flagi B na 2
            else begin                

                 B <= 16'h2;

                A1 <= 0;
                A2 <= 0;
                W <= temp[47:16];
            end
            gpio_out_s <= gpio_out_s + 1;

            mul_i <= 0;
            ones_i <= 0;
        end
    end


    assign gpio_out = gpio_out_s[15:0];
	assign sdata_out = sdata_out_s;
	assign gpio_in_s_insp = gpio_in_s;



endmodule

pliki/gpioemu_tb.v
`timescale 1ns/1ps

module gpioemu_tb;

    reg n_reset = 1;
    reg [15:0] saddress = 0;
    reg srd = 0;
    reg swr = 0;
    reg [31:0] sdata_in = 0;
    wire [31:0] sdata_out = 0;
    reg [31:0] gpio_in = 0;
    reg gpio_latch = 0;
    wire [31:0] gpio_out = 0;
    reg clk = 0;
    wire [31:0] gpio_in_s_insp = 0;
    wire [31:0] sdata_out_s = 0;




    integer i;

    initial begin
		$dumpfile("gpioemu.vcd");
		$dumpvars(0, gpioemu_tb);
		clk = 0;
	end


    always #1 clk <= ~clk;


    // Reset
    initial begin
        n_reset = 0;
        n_reset = 1;
    end

    initial begin


        // Sprawdzenie: 2 * 7 = 14

        #5 sdata_in = 24'h2;
        #5 saddress = 16'h108;
        #5 swr = 1;
        #5 swr = 0;

        #5 sdata_in = 24'h7;
        #5 saddress = 16'h110;
        #5 swr = 1;
        #5 swr = 0;

        #5 saddress = 16'h118; // Oczekiwany wynik W: E
        #5 srd = 1;
        #5 srd = 0;

	// Sprawdzenie: 7 * 2 = 14

        #5 sdata_in = 24'h7;
        #5 saddress = 16'h108;
        #5 swr = 1;
        #5 swr = 0;

        #5 sdata_in = 24'h2;
        #5 saddress = 16'h110;
        #5 swr = 1;
        #5 swr = 0;

        #5 saddress = 16'h118; // Oczekiwany wynik W: E
        #5 srd = 1;
        #5 srd = 0;


        // Sprawdzenie: 0 * 8 = 0


        #5 sdata_in = 24'h0;
        #5 saddress = 16'h108;
        #5 swr = 1;
        #5 swr = 0;

        #5 sdata_in = 24'h8;
        #5 saddress = 16'h110;
        #5 swr = 1;
        #5 swr = 0;

        #5 saddress = 16'h118; // Oczekiwany wynik W: 0
        #5 srd = 1;
        #5 srd = 0;

        #5 saddress = 16'h120; // Oczekiwany wynik L: 0
        #5 srd = 1;
        #5 srd = 0;

        #5 saddress = 16'h128; // Oczekiwany wynik B: 0
        #5 srd = 1;
        #5 srd = 0;



        // Sprawdzenie: 5 * 4 = 20


        #5 sdata_in = 24'h5;
        #5 saddress = 16'h108;
        #5 swr = 1;
        #5 swr = 0;

        #5 sdata_in = 24'h4;
        #5 saddress = 16'h110;
        #5 swr = 1;
        #5 swr = 0;

        #5 saddress = 16'h118; // Oczekiwany wynik W: 14
        #5 srd = 1;
        #5 srd = 0;

        #5 saddress = 16'h120; // Oczekiwany wynik L: 0
        #5 srd = 1;
        #5 srd = 0;

        #5 saddress = 16'h128; // Oczekiwany wynik B: 0
        #5 srd = 1;
        #5 srd = 0;




        // Sprawdzenie: 1 * 1 = 1


        #5 sdata_in = 24'h1;
        #5 saddress = 16'h108;
        #5 swr = 1;
        #5 swr = 0;

        #5 sdata_in = 24'h1;
        #5 saddress = 16'h110;
        #5 swr = 1;
        #5 swr = 0;

        #5 saddress = 16'h118; // Oczekiwany wynik W: 1
        #5 srd = 1;
        #5 srd = 0;

        #5 saddress = 16'h120; // Oczekiwany wynik L: 0
        #5 srd = 1;
        #5 srd = 0;

        #5 saddress = 16'h128; // Oczekiwany wynik B: 0
        #5 srd = 1;
        #5 srd = 0;



        // Sprawdzenie: 237 * 250 = 59 250


        #5 sdata_in = 24'hED;
        #5 saddress = 16'h108;
        #5 swr = 1;
        #5 swr = 0;

        #5 sdata_in = 24'hFA;
        #5 saddress = 16'h110;
        #5 swr = 1;
        #5 swr = 0;

        #5 saddress = 16'h118; // Oczekiwany wynik W: E772
        #5 srd = 1;
        #5 srd = 0;

        #5 saddress = 16'h120; // Oczekiwany wynik L: 0
        #5 srd = 1;
        #5 srd = 0;

        #5 saddress = 16'h128; // Oczekiwany wynik B: 0
        #5 srd = 1;
        #5 srd = 0;


        // Sprawdzenie przepełnienia


        #5 sdata_in = 24'hFFFFFF;
        #5 saddress = 16'h108;
        #5 swr = 1;
        #5 swr = 0;

        #5 sdata_in = 24'hFFFFFF;
        #5 saddress = 16'h110;
        #5 swr = 1;
        #5 swr = 0;

        #5 saddress = 16'h118; // Wynik W
        #5 srd = 1;
        #5 srd = 0;

        #5 saddress = 16'h120; // Oczekiwany wynik L: 0
        #5 srd = 1;
        #5 srd = 0;

        #5 saddress = 16'h128; // Oczekiwany wynik B: 0
        #5 srd = 1;
        #5 srd = 0;


        # 3000 $finish;
    end

    gpioemu e1(n_reset, saddress, srd, swr, sdata_in, sdata_out, gpio_in, gpio_latch, gpio_out, clk, gpio_in_s_insp);


endmodule

pliki/gpioemu.vcd
$date
	Wed Jun 14 14:26:44 2023
$end
$version
	Icarus Verilog
$end
$timescale
	1ps
$end
$scope module gpioemu_tb $end
$var wire 32 ! gpio_in_s_insp [31:0] $end
$var wire 32 " gpio_out [31:0] $end
$var wire 32 # sdata_out [31:0] $end
$var wire 32 $ sdata_out_s [31:0] $end
$var reg 1 % clk $end
$var reg 32 & gpio_in [31:0] $end
$var reg 1 ' gpio_latch $end
$var reg 1 ( n_reset $end
$var reg 16 ) saddress [15:0] $end
$var reg 32 * sdata_in [31:0] $end
$var reg 1 + srd $end
$var reg 1 , swr $end
$scope module e1 $end
$var wire 1 % clk $end
$var wire 32 - gpio_in [31:0] $end
$var wire 32 . gpio_in_s_insp [31:0] $end
$var wire 1 ' gpio_latch $end
$var wire 32 / gpio_out [31:0] $end
$var wire 1 ( n_reset $end
$var wire 16 0 saddress [15:0] $end
$var wire 32 1 sdata_in [31:0] $end
$var wire 32 2 sdata_out [31:0] $end
$var wire 1 + srd $end
$var wire 1 , swr $end
$var reg 24 3 A1 [23:0] $end
$var reg 24 4 A2 [23:0] $end
$var reg 2 5 B [1:0] $end
$var reg 32 6 L [31:0] $end
$var reg 32 7 W [31:0] $end
$var reg 32 8 gpio_in_s [31:0] $end
$var reg 32 9 gpio_out_s [31:0] $end
$var reg 32 : sdata_out_s [31:0] $end
$var reg 48 ; temp [47:0] $end
$var integer 32 < mul_i [31:0] $end
$var integer 32 = ones_i [31:0] $end
$upscope $end
$upscope $end
$enddefinitions $end
#0
$dumpvars
b0 =
b0 <
b0 ;
b0 :
b0 9
bx 8
b0 7
b0 6
b0 5
b0 4
b0 3
b0 2
b0 1
b0 0
b0 /
bx .
b0 -
0,
0+
b0 *
b0 )
1(
0'
b0 &
0%
b0 $
b0 #
b0 "
bx !
$end
#1000
1%
#2000
0%
#3000
1%
#4000
0%
#5000
1%
b10 *
b10 1
#6000
0%
#7000
1%
#8000
0%
#9000
1%
#10000
0%
b100001000 )
b100001000 0
#11000
1%
#12000
0%
#13000
1%
#14000
0%
#15000
b10 3
1%
1,
#16000
0%
#17000
1%
#18000
0%
#19000
1%
#20000
0%
0,
#21000
1%
#22000
0%
#23000
1%
#24000
0%
#25000
1%
b111 *
b111 1
#26000
0%
#27000
1%
#28000
0%
#29000
1%
#30000
0%
b100010000 )
b100010000 0
#31000
1%
#32000
0%
#33000
1%
#34000
0%
#35000
b0x "
b0x /
b1 9
b1110 7
b11 6
b0 =
b0 <
b0 ;
b0 5
b111 4
1%
1,
#36000
0%
#37000
1%
#38000
0%
#39000
1%
#40000
0%
0,
#41000
1%
#42000
0%
#43000
1%
#44000
0%
#45000
1%
b100011000 )
b100011000 0
#46000
0%
#47000
1%
#48000
0%
#49000
1%
#50000
b0xxx0 #
b0xxx0 2
b1110 :
0%
1+
#51000
1%
#52000
0%
#53000
1%
#54000
0%
#55000
1%
0+
#56000
0%
#57000
1%
#58000
0%
#59000
1%
#60000
0%
#61000
1%
#62000
0%
#63000
1%
#64000
0%
#65000
1%
b100001000 )
b100001000 0
#66000
0%
#67000
1%
#68000
0%
#69000
1%
#70000
b0 6
b0 7
b111 3
0%
1,
#71000
1%
#72000
0%
#73000
1%
#74000
0%
#75000
1%
0,
#76000
0%
#77000
1%
#78000
0%
#79000
1%
#80000
0%
b10 *
b10 1
#81000
1%
#82000
0%
#83000
1%
#84000
0%
#85000
1%
b100010000 )
b100010000 0
#86000
0%
#87000
1%
#88000
0%
#89000
1%
#90000
b1 5
b10 4
0%
1,
#91000
b0x0 "
b0x0 /
b10 9
b0 5
b1110 7
b11 6
b0 =
b0 ;
b0 <
1%
#92000
0%
#93000
1%
#94000
0%
#95000
1%
0,
#96000
0%
#97000
1%
#98000
0%
#99000
1%
#100000
0%
b100011000 )
b100011000 0
#101000
1%
#102000
0%
#103000
1%
#104000
0%
#105000
1%
1+
#106000
0%
#107000
1%
#108000
0%
#109000
1%
#110000
0%
0+
#111000
1%
#112000
0%
#113000
1%
#114000
0%
#115000
1%
b0 *
b0 1
#116000
0%
#117000
1%
#118000
0%
#119000
1%
#120000
0%
b100001000 )
b100001000 0
#121000
1%
#122000
0%
#123000
1%
#124000
0%
#125000
b0 6
b0 7
b0 3
1%
1,
#126000
0%
#127000
1%
#128000
0%
#129000
1%
#130000
0%
0,
#131000
1%
#132000
0%
#133000
1%
#134000
0%
#135000
1%
b1000 *
b1000 1
#136000
0%
#137000
1%
#138000
0%
#139000
1%
#140000
0%
b100010000 )
b100010000 0
#141000
1%
#142000
0%
#143000
1%
#144000
0%
#145000
b0xx "
b0xx /
b11 9
b0 =
b0 <
b0 5
b1000 4
1%
1,
#146000
0%
#147000
1%
#148000
0%
#149000
1%
#150000
0%
0,
#151000
1%
#152000
0%
#153000
1%
#154000
0%
#155000
1%
b100011000 )
b100011000 0
#156000
0%
#157000
1%
#158000
0%
#159000
1%
#160000
b0 #
b0 2
b0 :
0%
1+
#161000
1%
#162000
0%
#163000
1%
#164000
0%
#165000
1%
0+
#166000
0%
#167000
1%
#168000
0%
#169000
1%
#170000
0%
b100100000 )
b100100000 0
#171000
1%
#172000
0%
#173000
1%
#174000
0%
#175000
1%
1+
#176000
0%
#177000
1%
#178000
0%
#179000
1%
#180000
0%
0+
#181000
1%
#182000
0%
#183000
1%
#184000
0%
#185000
1%
b100101000 )
b100101000 0
#186000
0%
#187000
1%
#188000
0%
#189000
1%
#190000
0%
1+
#191000
1%
#192000
0%
#193000
1%
#194000
0%
#195000
1%
0+
#196000
0%
#197000
1%
#198000
0%
#199000
1%
#200000
0%
b101 *
b101 1
#201000
1%
#202000
0%
#203000
1%
#204000
0%
#205000
1%
b100001000 )
b100001000 0
#206000
0%
#207000
1%
#208000
0%
#209000
1%
#210000
b101 3
0%
1,
#211000
1%
#212000
0%
#213000
1%
#214000
0%
#215000
1%
0,
#216000
0%
#217000
1%
#218000
0%
#219000
1%
#220000
0%
b100 *
b100 1
#221000
1%
#222000
0%
#223000
1%
#224000
0%
#225000
1%
b100010000 )
b100010000 0
#226000
0%
#227000
1%
#228000
0%
#229000
1%
#230000
b1 5
b100 4
0%
1,
#231000
b0x00 "
b0x00 /
b100 9
b0 5
b10100 7
b10 6
b0 =
b0 ;
b0 <
1%
#232000
0%
#233000
1%
#234000
0%
#235000
1%
0,
#236000
0%
#237000
1%
#238000
0%
#239000
1%
#240000
0%
b100011000 )
b100011000 0
#241000
1%
#242000
0%
#243000
1%
#244000
0%
#245000
b0x0x00 #
b0x0x00 2
b10100 :
1%
1+
#246000
0%
#247000
1%
#248000
0%
#249000
1%
#250000
0%
0+
#251000
1%
#252000
0%
#253000
1%
#254000
0%
#255000
1%
b100100000 )
b100100000 0
#256000
0%
#257000
1%
#258000
0%
#259000
1%
#260000
b0x0 #
b0x0 2
b10 :
0%
1+
#261000
1%
#262000
0%
#263000
1%
#264000
0%
#265000
1%
0+
#266000
0%
#267000
1%
#268000
0%
#269000
1%
#270000
0%
b100101000 )
b100101000 0
#271000
1%
#272000
0%
#273000
1%
#274000
0%
#275000
b0 #
b0 2
b0 :
1%
1+
#276000
0%
#277000
1%
#278000
0%
#279000
1%
#280000
0%
0+
#281000
1%
#282000
0%
#283000
1%
#284000
0%
#285000
1%
b1 *
b1 1
#286000
0%
#287000
1%
#288000
0%
#289000
1%
#290000
0%
b100001000 )
b100001000 0
#291000
1%
#292000
0%
#293000
1%
#294000
0%
#295000
b0 6
b0 7
b1 3
1%
1,
#296000
0%
#297000
1%
#298000
0%
#299000
1%
#300000
0%
0,
#301000
1%
#302000
0%
#303000
1%
#304000
0%
#305000
1%
#306000
0%
#307000
1%
#308000
0%
#309000
1%
#310000
0%
b100010000 )
b100010000 0
#311000
1%
#312000
0%
#313000
1%
#314000
0%
#315000
b0x0x "
b0x0x /
b101 9
b1 7
b0 =
b1 6
b0 <
b0 ;
b0 5
b1 4
1%
1,
#316000
0%
#317000
1%
#318000
0%
#319000
1%
#320000
0%
0,
#321000
1%
#322000
0%
#323000
1%
#324000
0%
#325000
1%
b100011000 )
b100011000 0
#326000
0%
#327000
1%
#328000
0%
#329000
1%
#330000
b0x #
b0x 2
b1 :
0%
1+
#331000
1%
#332000
0%
#333000
1%
#334000
0%
#335000
1%
0+
#336000
0%
#337000
1%
#338000
0%
#339000
1%
#340000
0%
b100100000 )
b100100000 0
#341000
1%
#342000
0%
#343000
1%
#344000
0%
#345000
1%
1+
#346000
0%
#347000
1%
#348000
0%
#349000
1%
#350000
0%
0+
#351000
1%
#352000
0%
#353000
1%
#354000
0%
#355000
1%
b100101000 )
b100101000 0
#356000
0%
#357000
1%
#358000
0%
#359000
1%
#360000
b0 #
b0 2
b0 :
0%
1+
#361000
1%
#362000
0%
#363000
1%
#364000
0%
#365000
1%
0+
#366000
0%
#367000
1%
#368000
0%
#369000
1%
#370000
0%
b11101101 *
b11101101 1
#371000
1%
#372000
0%
#373000
1%
#374000
0%
#375000
1%
b100001000 )
b100001000 0
#376000
0%
#377000
1%
#378000
0%
#379000
1%
#380000
b0 6
b0 7
b11101101 3
0%
1,
#381000
1%
#382000
0%
#383000
1%
#384000
0%
#385000
1%
0,
#386000
0%
#387000
1%
#388000
0%
#389000
1%
#390000
0%
b11111010 *
b11111010 1
#391000
1%
#392000
0%
#393000
1%
#394000
0%
#395000
1%
b100010000 )
b100010000 0
#396000
0%
#397000
1%
#398000
0%
#399000
1%
#400000
b1 5
b11111010 4
0%
1,
#401000
b0xx0 "
b0xx0 /
b110 9
b0 5
b1110011101110010 7
b1010 6
b0 =
b0 ;
b0 <
1%
#402000
0%
#403000
1%
#404000
0%
#405000
1%
0,
#406000
0%
#407000
1%
#408000
0%
#409000
1%
#410000
0%
b100011000 )
b100011000 0
#411000
1%
#412000
0%
#413000
1%
#414000
0%
#415000
b0xxx00xxx0xxx00x0 #
b0xxx00xxx0xxx00x0 2
b1110011101110010 :
1%
1+
#416000
0%
#417000
1%
#418000
0%
#419000
1%
#420000
0%
0+
#421000
1%
#422000
0%
#423000
1%
#424000
0%
#425000
1%
b100100000 )
b100100000 0
#426000
0%
#427000
1%
#428000
0%
#429000
1%
#430000
b0x0x0 #
b0x0x0 2
b1010 :
0%
1+
#431000
1%
#432000
0%
#433000
1%
#434000
0%
#435000
1%
0+
#436000
0%
#437000
1%
#438000
0%
#439000
1%
#440000
0%
b100101000 )
b100101000 0
#441000
1%
#442000
0%
#443000
1%
#444000
0%
#445000
b0 #
b0 2
b0 :
1%
1+
#446000
0%
#447000
1%
#448000
0%
#449000
1%
#450000
0%
0+
#451000
1%
#452000
0%
#453000
1%
#454000
0%
#455000
1%
b111111111111111111111111 *
b111111111111111111111111 1
#456000
0%
#457000
1%
#458000
0%
#459000
1%
#460000
0%
b100001000 )
b100001000 0
#461000
1%
#462000
0%
#463000
1%
#464000
0%
#465000
b0 6
b0 7
b111111111111111111111111 3
1%
1,
#466000
0%
#467000
1%
#468000
0%
#469000
1%
#470000
0%
0,
#471000
1%
#472000
0%
#473000
1%
#474000
0%
#475000
1%
#476000
0%
#477000
1%
#478000
0%
#479000
1%
#480000
0%
b100010000 )
b100010000 0
#481000
1%
#482000
0%
#483000
1%
#484000
0%
#485000
b0xxx "
b0xxx /
b111 9
b1111111111111111111111010000000 7
b0 3
b0 =
b11000 6
b0 <
b0 ;
b10 5
b0 4
1%
1,
#486000
0%
#487000
1%
#488000
0%
#489000
1%
#490000
0%
0,
#491000
1%
#492000
0%
#493000
1%
#494000
0%
#495000
1%
b100011000 )
b100011000 0
#496000
0%
#497000
1%
#498000
0%
#499000
1%
#500000
b0xxxxxxxxxxxxxxxxxxxxxx0x0000000 #
b0xxxxxxxxxxxxxxxxxxxxxx0x0000000 2
b1111111111111111111111010000000 :
0%
1+
#501000
1%
#502000
0%
#503000
1%
#504000
0%
#505000
1%
0+
#506000
0%
#507000
1%
#508000
0%
#509000
1%
#510000
0%
b100100000 )
b100100000 0
#511000
1%
#512000
0%
#513000
1%
#514000
0%
#515000
b0xx000 #
b0xx000 2
b11000 :
1%
1+
#516000
0%
#517000
1%
#518000
0%
#519000
1%
#520000
0%
0+
#521000
1%
#522000
0%
#523000
1%
#524000
0%
#525000
1%
b100101000 )
b100101000 0
#526000
0%
#527000
1%
#528000
0%
#529000
1%
#530000
b0x0 #
b0x0 2
b10 :
0%
1+
#531000
1%
#532000
0%
#533000
1%
#534000
0%
#535000
1%
0+
